setup.py
CTHub/CTHub
CTHub/__init__.py
CTHub/configure.txt
CTHub.egg-info/PKG-INFO
CTHub.egg-info/SOURCES.txt
CTHub.egg-info/dependency_links.txt
CTHub.egg-info/top_level.txt