Metadata-Version: 1.1
Name: CTHub
Version: 0.2
Summary: Create Track Hub
Home-page: http://www.calyx.biz/
Author: Yingxiang Li
Author-email: xlccalyx@gmail.com
License: GPLv3
Download-URL: https://pypi.python.org/pypi/CTHub
Keywords: Create Track Hub
Platform: UNKNOWN
Classifier: Development Status :: 3 - Alpha
Classifier: Intended Audience :: Developers
Classifier: Topic :: Software Development :: Build Tools
Classifier: License :: OSI Approved :: GNU General Public License v3 (GPLv3)
Classifier: Programming Language :: Python :: 2.7
